README
setup.py
zsearch_definitions/__init__.py
zsearch_definitions/admin.py
zsearch_definitions/anonstore.py
zsearch_definitions/anonstore_pb2.py
zsearch_definitions/caa_pb2.py
zsearch_definitions/certificate_pb2.py
zsearch_definitions/common_pb2.py
zsearch_definitions/ct_pb2.py
zsearch_definitions/hoststore.py
zsearch_definitions/hoststore_pb2.py
zsearch_definitions/protocols.py
zsearch_definitions/protocols_pb2.py
zsearch_definitions/pubkey_pb2.py
zsearch_definitions/query.py
zsearch_definitions/rpc_pb2.py
zsearch_definitions/rpc_pb2_grpc.py
zsearch_definitions/search_pb2.py
zsearch_definitions/search_pb2_grpc.py
zsearch_definitions/zlint.py
zsearch_definitions/zlint_pb2.py
zsearch_definitions.egg-info/PKG-INFO
zsearch_definitions.egg-info/SOURCES.txt
zsearch_definitions.egg-info/dependency_links.txt
zsearch_definitions.egg-info/not-zip-safe
zsearch_definitions.egg-info/requires.txt
zsearch_definitions.egg-info/top_level.txt