Metadata-Version: 1.0
Name: zsearch-definitions
Version: 0.1.26
Summary: Egg version of files that can be used for interacting with zdb through python
Home-page: UNKNOWN
Author: Censys Team
Author-email: team@censys.io
License: Apache License, Version 2.0
Keywords: python json zsearch
Platform: UNKNOWN
